guajillo-0.2.0.dist-info/METADATA
guajillo-0.2.0.dist-info/WHEEL
guajillo-0.2.0.dist-info/entry_points.txt
guajillo/__init__.py
guajillo/app.py
guajillo/exceptions.py
guajillo/main.py
guajillo/outputs/__init__.py
guajillo/outputs/boolean.py
guajillo/outputs/highstate.py
guajillo/outputs/json.py
guajillo/outputs/non_returns.py
guajillo/outputs/profile.py
guajillo/outputs/yaml.py
guajillo/utils/__init__.py
guajillo/utils/cli.py
guajillo/utils/conn.py
guajillo/utils/console.py
guajillo/utils/outputs.py
guajillo/version.py
guajillo-0.2.0.dist-info/RECORD
